setup.cfg
setup.py
dist_alx/Gaussian.py
dist_alx/__init__.py
ssllaavvaa.egg-info/PKG-INFO
ssllaavvaa.egg-info/SOURCES.txt
ssllaavvaa.egg-info/dependency_links.txt
ssllaavvaa.egg-info/not-zip-safe
ssllaavvaa.egg-info/top_level.txt