Metadata-Version: 2.1
Name: ssllaavvaa
Version: 1.1
Summary: Gaussian and Binomial distributions
Author-email: sv14.04@mail.ru
